{
  "type": "Collection",
  "id": "products",
  "title": "Products",
  "stac_version": "1.0.0",
  "description": "Geoscience products representing the measured or inferred values of one or more variables over a given time range and spatial area.",
  "links": [
    {
      "rel": "root",
      "href": "../catalog.json",
      "type": "application/json"
    },
    {
      "rel": "child",
      "href": "./doppler-derived-surface-current-world-ocean-circulation/collection.json",
      "type": "application/json",
      "title": "Sentinel-1 IW Ocean Surface Current Radial Velocity product in Agulhas current"
    }
  ],
  "stac_extensions": [],
  "extent": {
    "spatial": {
      "bbox": [[-180.0, -90.0, 180.0, 90.0]]
    },
    "temporal": {
      "interval": [
        ["2019-05-08T16:44:03.750000Z", "2020-04-29T17:17:48.750000Z"]
      ]
    }
  },
  "license": "proprietary"
}
