{
  "type": "Catalog",
  "id": "Photosynthetically Active Radiation (PAR)",
  "stac_version": "1.0.0",
  "description": "Flux of downwelling photons of wavelength 0.4-0.7",
  "links": [
    {
      "rel": "root",
      "href": "../../catalog.json",
      "type": "application/json",
      "title": "Open Science Catalog"
    },
    {
      "rel": "via",
      "href": "https://space.oscar.wmo.int/variables/view/photosynthetically_active_radiation_par",
      "type": "text/html",
      "title": "Description"
    },
    {
      "rel": "related",
      "href": "../../themes/Atmosphere/catalog.json",
      "type": "application/json",
      "title": "Theme: Atmosphere"
    },
    {
      "rel": "parent",
      "href": "../catalog.json",
      "type": "application/json",
      "title": "Variables"
    }
  ],
  "stac_extensions": [],
  "title": "Photosynthetically Active Radiation (PAR)"
}