{
  "type": "Catalog",
  "id": "Solar radio flux spectrum",
  "stac_version": "1.0.0",
  "description": "Solar radio flux energy spectrum integrated over the solar disk.",
  "links": [
    {
      "rel": "root",
      "href": "../../catalog.json",
      "type": "application/json",
      "title": "Open Science Catalog"
    },
    {
      "rel": "via",
      "href": "https://space.oscar.wmo.int/variables/view/solar_radio_flux_spectrum",
      "type": "text/html",
      "title": "Description"
    },
    {
      "rel": "related",
      "href": "../../themes/Magnetosphere_Ionosphere/catalog.json",
      "type": "application/json",
      "title": "Theme: Magnetosphere_Ionosphere"
    },
    {
      "rel": "parent",
      "href": "../catalog.json",
      "type": "application/json",
      "title": "Variables"
    }
  ],
  "stac_extensions": [],
  "title": "Solar radio flux spectrum"
}